mapboxgl/__init__.py
mapboxgl/colors.py
mapboxgl/errors.py
mapboxgl/templates.py
mapboxgl/utils.py
mapboxgl/viz.py
mapboxgl/templates/base.html
mapboxgl/templates/choropleth.html
mapboxgl/templates/circle.html
mapboxgl/templates/clustered_circle.html
mapboxgl/templates/export_canvas.html
mapboxgl/templates/graduated_circle.html
mapboxgl/templates/heatmap.html
mapboxgl/templates/image.html
mapboxgl/templates/linestring.html
mapboxgl/templates/main.html
mapboxgl/templates/map.html
mapboxgl/templates/raster.html
mapboxgl/templates/symbol.html
mapboxgl/templates/vector_choropleth.html
mapboxgl/templates/vector_circle.html
mapboxgl/templates/vector_graduated_circle.html
mapboxgl/templates/vector_heatmap.html
mapboxgl/templates/vector_linestring.html
mapboxgl/templates/vector_map.html
mapboxgl-0.10.1.dist-info/METADATA
mapboxgl-0.10.1.dist-info/RECORD
mapboxgl-0.10.1.dist-info/WHEEL
mapboxgl-0.10.1.dist-info/top_level.txt
