Metadata-Version: 2.1
Name: mapboxgl
Version: 0.10.1
Summary: MapboxGL plugin for Jupyter Notebooks
Home-page: https://github.com/mapbox/mapboxgl-jupyter
Author: Ryan Baumann
License: MIT
Platform: UNKNOWN
Classifier: Development Status :: 1 - Planning
Classifier: Intended Audience :: Developers
Classifier: Intended Audience :: Science/Research
Classifier: License :: OSI Approved :: MIT License
Classifier: Programming Language :: Python :: 2
Classifier: Programming Language :: Python :: 3
Classifier: Topic :: Multimedia :: Graphics :: Graphics Conversion
Classifier: Topic :: Scientific/Engineering :: GIS
Provides-Extra: test
